aeroevap/__init__.py
aeroevap/aero.py
AeroEvap-0.0.2.post3.dist-info/LICENSE.txt
AeroEvap-0.0.2.post3.dist-info/LICENSE.txt~
AeroEvap-0.0.2.post3.dist-info/METADATA
AeroEvap-0.0.2.post3.dist-info/WHEEL
AeroEvap-0.0.2.post3.dist-info/top_level.txt
AeroEvap-0.0.2.post3.dist-info/RECORD
