Metadata-Version: 2.1
Name: AeroEvap
Version: 0.0.2.post3
Summary: Aerodynamic mass-transfer approach for open-water evaporation
Home-page: https://github.com/WSWUP/AeroEvap
Author: Chris Pearson and John Volk
Author-email: john.volk@dri.edu
License: BSD3
Platform: Windows
Platform: Linux
Platform: Mac OS X
Classifier: License :: OSI Approved :: BSD License
Classifier: Programming Language :: Python :: 3.7
Classifier: Environment :: Console
Classifier: Development Status :: 4 - Beta
Classifier: Topic :: Scientific/Engineering
Classifier: Intended Audience :: Science/Research
Requires-Python: >=3.7
Requires-Dist: numpy
Requires-Dist: pandas
Requires-Dist: matplotlib
